src/__init__.py
src/inspetor_client.py
src/inspetor_resource.py
src/snowplow_manager.py
src/inspetor/__init__.py
src/inspetor/inspetor_json_encoder.py
src/inspetor/exception/__init__.py
src/inspetor/exception/exception_abstract.py
src/inspetor/exception/tracker_exception.py
src/inspetor/exception/model_exception/__init__.py
src/inspetor/exception/model_exception/inspetor_account_exception.py
src/inspetor/exception/model_exception/inspetor_address_exception.py
src/inspetor/exception/model_exception/inspetor_auth_exception.py
src/inspetor/exception/model_exception/inspetor_category_exception.py
src/inspetor/exception/model_exception/inspetor_credit_card_exception.py
src/inspetor/exception/model_exception/inspetor_event_exception.py
src/inspetor/exception/model_exception/inspetor_general_exception.py
src/inspetor/exception/model_exception/inspetor_item_exception.py
src/inspetor/exception/model_exception/inspetor_pass_recovery_exception.py
src/inspetor/exception/model_exception/inspetor_payment_exception.py
src/inspetor/exception/model_exception/inspetor_sale_exception.py
src/inspetor/exception/model_exception/inspetor_session_exception.py
src/inspetor/exception/model_exception/inspetor_transfer_exception.py
src/inspetor/model/__init__.py
src/inspetor/model/inspetor_abstract_model.py
src/inspetor/model/inspetor_account.py
src/inspetor/model/inspetor_address.py
src/inspetor/model/inspetor_auth.py
src/inspetor/model/inspetor_category.py
src/inspetor/model/inspetor_credit_card.py
src/inspetor/model/inspetor_event.py
src/inspetor/model/inspetor_item.py
src/inspetor/model/inspetor_pass_recovery.py
src/inspetor/model/inspetor_payment.py
src/inspetor/model/inspetor_sale.py
src/inspetor/model/inspetor_session.py
src/inspetor/model/inspetor_transfer.py
tests/__init__.py
tests/inspetor/__init__.py
tests/inspetor/integration/__init__.py
tests/inspetor/integration/integration_test.py
tests/inspetor/model/__init__.py
tests/inspetor/model/inspetor_account_test.py
inspetor-0.0.3.dist-info/LICENSE
inspetor-0.0.3.dist-info/METADATA
inspetor-0.0.3.dist-info/WHEEL
inspetor-0.0.3.dist-info/top_level.txt
inspetor-0.0.3.dist-info/RECORD
