Metadata-Version: 2.1
Name: inspetor
Version: 0.0.3
Summary: Inspetor Antifraud library for Python.
Home-page: https://github.com/pypa/sampleproject
Author: Inspetor Dev Team
Author-email: dev@useinspetor.com
License: UNKNOWN
Platform: UNKNOWN
Classifier: Programming Language :: Python :: 3
Classifier: License :: OSI Approved :: MIT License
Classifier: Operating System :: OS Independent
